scenera/node/__init__.py
scenera/node/scenemark.py
scenera/node/spec.py
scenera.node-0.1.1.dist-info/METADATA
scenera.node-0.1.1.dist-info/WHEEL
scenera.node-0.1.1.dist-info/top_level.txt
scenera.node-0.1.1.dist-info/RECORD
