Metadata-Version: 2.1
Name: scenera.node
Version: 0.1.1
Summary: Scenera Node SDK
Home-page: https://medium-multiply.readthedocs.io/
Author: Dirk Meulenbelt
Author-email: dirkmeulenbelt@gmail.com
License: MIT
Platform: UNKNOWN
Classifier: Intended Audience :: Developers
Classifier: License :: OSI Approved :: MIT License
Classifier: Programming Language :: Python
Classifier: Programming Language :: Python :: 3
Classifier: Programming Language :: Python :: 3.6
Classifier: Programming Language :: Python :: 3.7
Classifier: Programming Language :: Python :: 3.8
Classifier: Programming Language :: Python :: 3.9
Classifier: Operating System :: OS Independent
Requires-Dist: jsonschema
Requires-Dist: requests
